bq_sqoop-0.0.13.data/scripts/bq-sqoop
bq_sqoop-0.0.13.dist-info/METADATA
bq_sqoop-0.0.13.dist-info/RECORD
bq_sqoop-0.0.13.dist-info/WHEEL
bq_sqoop-0.0.13.dist-info/top_level.txt
bqsqoop/__init__.py
bqsqoop/job.py
bqsqoop/extractor/__init__.py
bqsqoop/extractor/iextractor.py
bqsqoop/extractor/elasticsearch/__init__.py
bqsqoop/extractor/elasticsearch/elasticsearch.py
bqsqoop/extractor/elasticsearch/helper.py
bqsqoop/extractor/sql/__init__.py
bqsqoop/extractor/sql/helper.py
bqsqoop/extractor/sql/sql.py
bqsqoop/utils/__init__.py
bqsqoop/utils/async_worker.py
bqsqoop/utils/errors.py
bqsqoop/utils/log.py
bqsqoop/utils/math_util.py
bqsqoop/utils/pandas_util.py
bqsqoop/utils/parquet_util.py
bqsqoop/utils/progressbar_util.py
bqsqoop/utils/typed.py
bqsqoop/utils/gcloud/__init__.py
bqsqoop/utils/gcloud/auth.py
bqsqoop/utils/gcloud/bigquery.py
bqsqoop/utils/gcloud/job.py
bqsqoop/utils/gcloud/storage.py
