Metadata-Version: 2.1
Name: bq-sqoop
Version: 0.0.13
Summary: A CLI client for exporting elasticsearch data to csv
Home-page: https://github.com/therako/bqsqoop
Author: Arun Kumar Ramanathan
Author-email: therealrako@gmail.com
License: MIT License
Platform: UNKNOWN
Classifier: License :: OSI Approved :: MIT License
Classifier: Development Status :: 2 - Pre-Alpha
Classifier: Operating System :: OS Independent
Classifier: Programming Language :: Python
Classifier: Programming Language :: Python :: 3
Classifier: Programming Language :: Python :: 3.6
Requires-Dist: toml
Requires-Dist: tqdm (==4.19.8)
Requires-Dist: numpy (==1.14.5)
Requires-Dist: pandas (==0.23.1)
Requires-Dist: pytz (==2018.4)
Requires-Dist: gcloud (==0.18.3)
Requires-Dist: google-cloud-storage (==1.10.0)
Requires-Dist: google-cloud-bigquery (==1.3.0)
Requires-Dist: Cython (==0.28.4)
Requires-Dist: pyarrow (==0.10.0)
Requires-Dist: elasticsearch (<7.0.0,>=6.0.0)
Requires-Dist: elasticsearch-dsl (<7.0.0,>=6.0.0)
Requires-Dist: sqlalchemy (==1.2.10)
Requires-Dist: psycopg2 (==2.7)
Requires-Dist: futures; python_version == "2.7"
